[
    {
        "bigImg" : 7801,
        "smlImg1" : 8699,
        "smlImg2" : 0,
        "smlImg3" : 0,
        "price" : 350
    },
    {
        "bigImg" : 8538,
        "smlImg1" : 7636,
        "smlImg2" : 0,
        "smlImg3" : 0,
        "price" : 385
    },
    {
        "bigImg" : 8766,
        "smlImg1" : 8768,
        "smlImg2" : 8759,
        "smlImg3" : 8772,
        "price" : 385
    },
    {
        "bigImg" : 9003,
        "smlImg1" : 9034,
        "smlImg2" : 0,
        "smlImg3" : 0,
        "price" : 495
    },
    {
        "bigImg" : 9043,
        "smlImg1" : 9059,
        "smlImg2" : 0,
        "smlImg3" : 0,
        "price" : 495
    },
    {
        "bigImg" : 9055,
        "smlImg1" : 9057,
        "smlImg2" : 9013,
        "smlImg3" : 9014,
        "price" : 1100
    },
    {
        "bigImg" : 7741,
        "smlImg1" : 7573,
        "smlImg2" : 0,
        "smlImg3" : 0,
        "price" : 100
    }
]
